src/user_source/hdl_source/SD/dual_key_long_hold_guard.v
`timescale 1ns/1ps

module dual_key_long_hold_guard #(
    parameter integer DEBOUNCE_CYCLES = 1000000,
    parameter integer HOLD_CYCLES = 100000000
) (
    input  wire clk,
    input  wire rst_n,
    input  wire enabled,
    input  wire key2_n,
    input  wire key3_n,
    output reg  trigger,
    output reg  locked,
    output reg  key2_stable_n,
    output reg  key3_stable_n
);
    localparam integer DB_BITS = (DEBOUNCE_CYCLES <= 2) ? 1 : $clog2(DEBOUNCE_CYCLES);
    localparam integer HOLD_BITS = (HOLD_CYCLES <= 2) ? 1 : $clog2(HOLD_CYCLES);

    reg key2_sync1, key2_sync2;
    reg key3_sync1, key3_sync2;
    reg [DB_BITS-1:0] key2_count;
    reg [DB_BITS-1:0] key3_count;
    reg [HOLD_BITS-1:0] hold_count;

    initial begin
        if (DEBOUNCE_CYCLES < 1 || HOLD_CYCLES < 1) begin
            $display("DUAL_KEY_GUARD_CONFIG_ERROR invalid timing parameter");
            $finish;
        end
    end

    always @(posedge clk or negedge rst_n) begin
        if (!rst_n) begin
            key2_sync1 <= 1'b1;
            key2_sync2 <= 1'b1;
            key3_sync1 <= 1'b1;
            key3_sync2 <= 1'b1;
        end else begin
            key2_sync1 <= key2_n;
            key2_sync2 <= key2_sync1;
            key3_sync1 <= key3_n;
            key3_sync2 <= key3_sync1;
        end
    end

    always @(posedge clk or negedge rst_n) begin
        if (!rst_n) begin
            key2_count <= {DB_BITS{1'b0}};
            key3_count <= {DB_BITS{1'b0}};
            key2_stable_n <= 1'b1;
            key3_stable_n <= 1'b1;
            hold_count <= {HOLD_BITS{1'b0}};
            trigger <= 1'b0;
            locked <= 1'b0;
        end else begin
            trigger <= 1'b0;
            if (key2_sync2 == key2_stable_n)
                key2_count <= {DB_BITS{1'b0}};
            else if (key2_count + 1 >= DEBOUNCE_CYCLES) begin
                key2_count <= {DB_BITS{1'b0}};
                key2_stable_n <= key2_sync2;
            end else key2_count <= key2_count + 1'b1;

            if (key3_sync2 == key3_stable_n)
                key3_count <= {DB_BITS{1'b0}};
            else if (key3_count + 1 >= DEBOUNCE_CYCLES) begin
                key3_count <= {DB_BITS{1'b0}};
                key3_stable_n <= key3_sync2;
            end else key3_count <= key3_count + 1'b1;

            if (!enabled || locked || key2_stable_n || key3_stable_n) begin
                hold_count <= {HOLD_BITS{1'b0}};
            end else if (hold_count + 1 >= HOLD_CYCLES) begin
                hold_count <= {HOLD_BITS{1'b0}};
                trigger <= 1'b1;
                locked <= 1'b1;
            end else begin
                hold_count <= hold_count + 1'b1;
            end
        end
    end
endmodule

src/user_source/hdl_source/SD/dual_key_chord_router.v
`timescale 1ns/1ps

module dual_key_chord_router #(
    parameter integer DEBOUNCE_CYCLES = 1000000,
    parameter integer HOLD_CYCLES = 100000000,
    // KEY3 held alone for this long, then released, emits key3_long_event
    // (brightness ladder) instead of the single-click auto toggle.
    parameter integer KEY3_LONG_CYCLES = 50000000
) (
    input  wire clk,
    input  wire rst_n,
    input  wire save_enabled,
    input  wire key2_n,
    input  wire key3_n,
    output reg  key2_event,
    output reg  key3_event,
    output reg  key3_long_event,
    output wire save_event,
    output wire save_locked,
    output wire key2_stable_n,
    output wire key3_stable_n
);
    localparam [1:0] ST_IDLE = 2'd0;
    localparam [1:0] ST_KEY2 = 2'd1;
    localparam [1:0] ST_KEY3 = 2'd2;
    localparam [1:0] ST_CHORD = 2'd3;

    reg [1:0] state;
    reg save_armed;
    wire guard_trigger;
    reg [31:0] key3_hold_count;
    reg key3_long_marked;

    initial begin
        if (DEBOUNCE_CYCLES < 1 || HOLD_CYCLES < 1) begin
            $display("DUAL_KEY_CHORD_ROUTER_CONFIG_ERROR invalid timing parameter");
            $finish;
        end
    end

    dual_key_long_hold_guard #(
        .DEBOUNCE_CYCLES(DEBOUNCE_CYCLES),
        .HOLD_CYCLES(HOLD_CYCLES)
    ) u_guard (
        .clk(clk), .rst_n(rst_n),
        .enabled(save_enabled && save_armed && state == ST_CHORD),
        .key2_n(key2_n), .key3_n(key3_n), .trigger(guard_trigger),
        .locked(save_locked), .key2_stable_n(key2_stable_n),
        .key3_stable_n(key3_stable_n)
    );

    assign save_event = guard_trigger;

    always @(posedge clk or negedge rst_n) begin
        if (!rst_n) begin
            state <= ST_IDLE;
            save_armed <= 1'b0;
            key2_event <= 1'b0;
            key3_event <= 1'b0;
            key3_long_event <= 1'b0;
            key3_hold_count <= 32'd0;
            key3_long_marked <= 1'b0;
        end else begin
            key2_event <= 1'b0;
            key3_event <= 1'b0;
            key3_long_event <= 1'b0;

            if (!save_enabled)
                save_armed <= 1'b0;
            else if (key2_stable_n && key3_stable_n)
                save_armed <= 1'b1;

            case (state)
                ST_IDLE: begin
                    if (!key2_stable_n && !key3_stable_n)
                        state <= ST_CHORD;
                    else if (!key2_stable_n)
                        state <= ST_KEY2;
                    else if (!key3_stable_n) begin
                        state <= ST_KEY3;
                        key3_hold_count <= 32'd0;
                        key3_long_marked <= 1'b0;
                    end
                end
                ST_KEY2: begin
                    if (!key2_stable_n && !key3_stable_n) begin
                        state <= ST_CHORD;
                    end else if (key2_stable_n) begin
                        key2_event <= 1'b1;
                        state <= key3_stable_n ? ST_IDLE : ST_KEY3;
                    end
                end
                ST_KEY3: begin
                    if (!key2_stable_n && !key3_stable_n) begin
                        // KEY2 joining cancels the long-press ladder and
                        // hands the pair to the save chord.
                        state <= ST_CHORD;
                        key3_hold_count <= 32'd0;
                        key3_long_marked <= 1'b0;
                    end else if (key3_stable_n) begin
                        if (key3_long_marked)
                            key3_long_event <= 1'b1;
                        else
                            key3_event <= 1'b1;
                        key3_hold_count <= 32'd0;
                        key3_long_marked <= 1'b0;
                        state <= key2_stable_n ? ST_IDLE : ST_KEY2;
                    end else if (key3_hold_count < KEY3_LONG_CYCLES) begin
                        key3_hold_count <= key3_hold_count + 1'b1;
                        if (key3_hold_count == KEY3_LONG_CYCLES - 1)
                            key3_long_marked <= 1'b1;
                    end
                end
                ST_CHORD: begin
                    if (key2_stable_n && key3_stable_n)
                        state <= ST_IDLE;
                end
                default: state <= ST_IDLE;
            endcase
            end
    end
endmodule

sim/tb_router.v
`timescale 1ns/1ps
// TB: dual_key_chord_router 行为冒烟（参数缩小加速仿真，不进 TD 工程）
module tb_router;
    reg clk = 0;
    reg rst_n = 0;
    reg key2_n = 1, key3_n = 1;
    wire key2_event, key3_event, key3_long_event, save_event, save_locked;

    localparam integer DEB = 100;    // 100 cycles debounce
    localparam integer HOLD = 2000;  // 2000 cycles chord hold
    localparam integer LONG3 = 1000; // 1000 cycles key3 long

    dual_key_chord_router #(
        .DEBOUNCE_CYCLES(DEB),
        .HOLD_CYCLES(HOLD),
        .KEY3_LONG_CYCLES(LONG3)
    ) dut (
        .clk(clk), .rst_n(rst_n), .save_enabled(1'b1),
        .key2_n(key2_n), .key3_n(key3_n),
        .key2_event(key2_event), .key3_event(key3_event),
        .key3_long_event(key3_long_event),
        .save_event(save_event), .save_locked(save_locked),
        .key2_stable_n(), .key3_stable_n()
    );

    always #5 clk = ~clk; // 100MHz, 周期 10ns

    integer n_key2 = 0, n_key3 = 0, n_long = 0, n_save = 0;
    always @(posedge clk) begin
        if (key2_event) n_key2 = n_key2 + 1;
        if (key3_event) n_key3 = n_key3 + 1;
        if (key3_long_event) n_long = n_long + 1;
        if (save_event) n_save = n_save + 1;
    end

    task cyc(input integer n);   // 等 n 个时钟周期
        repeat (n) @(posedge clk);
    endtask

    initial begin
        rst_n = 0; cyc(2*DEB); rst_n = 1; cyc(2*DEB);

        // 用例1: KEY2 单击 -> 1 个 key2_event
        key2_n = 0; cyc(2*DEB); key2_n = 1; cyc(2*DEB);
        if (n_key2 !== 1) $display("FAIL case1: n_key2=%0d", n_key2);
        else $display("PASS case1: KEY2 single click -> key2_event");

        // 用例2: KEY3 单击 -> 1 个 key3_event
        key3_n = 0; cyc(2*DEB); key3_n = 1; cyc(2*DEB);
        if (n_key3 !== 1) $display("FAIL case2: n_key3=%0d", n_key3);
        else $display("PASS case2: KEY3 single click -> key3_event");

        // 用例3: KEY3 长按超过 LONG3 再松开 -> 1 个 key3_long_event，0 个新增 key3_event
        key3_n = 0; cyc(2*LONG3); key3_n = 1; cyc(2*DEB);
        if (n_long !== 1 || n_key3 !== 1) $display("FAIL case3: n_long=%0d n_key3=%0d", n_long, n_key3);
        else $display("PASS case3: KEY3 long hold -> key3_long_event once, no toggle");

        // 用例4: KEY3 长按 3 倍时长不松 -> 仍只 1 次（marked 防重复）
        key3_n = 0; cyc(3*LONG3); key3_n = 1; cyc(2*DEB);
        if (n_long !== 2) $display("FAIL case4: n_long=%0d", n_long);
        else $display("PASS case4: KEY3 held 3x duration -> exactly one long event");

        // 用例5: 双键同按超过 HOLD -> 1 个 save_event
        key2_n = 0; key3_n = 0; cyc(2*HOLD); key2_n = 1; key3_n = 1; cyc(2*DEB);
        if (n_save !== 1) $display("FAIL case5: n_save=%0d", n_save);
        else $display("PASS case5: chord hold -> save_event once");
        if (!save_locked) $display("FAIL case5b: save_locked not asserted");
        else $display("PASS case5b: save_locked latched");

        // 用例6: save 之后组合键不再触发（locked，一次上电一次保存）
        key2_n = 0; key3_n = 0; cyc(3*HOLD); key2_n = 1; key3_n = 1; cyc(2*DEB);
        if (n_save !== 1) $display("FAIL case6: n_save=%0d (should stay 1)", n_save);
        else $display("PASS case6: no second save after locked");

        // 用例7: 单击后快速补按另一键（无 CHORD 误触发 save）
        key2_n = 0; cyc(2*DEB); key2_n = 1; cyc(2*DEB);
        key3_n = 0; cyc(2*DEB); key3_n = 1; cyc(2*DEB);
        if (n_save !== 1) $display("FAIL case7: n_save=%0d", n_save);
        else $display("PASS case7: sequential presses produce no save");

        $display("ALL CASES DONE");
        $finish;
    end
endmodule

sim/tb_router.vcd
$date
	Mon Oct  5 11:14:55 2026
$end
$version
	Icarus Verilog
$end
$timescale
	1ps
$end
$scope module tb_router $end
$var wire 1 ! save_locked $end
$var wire 1 " save_event $end
$var wire 1 # key3_long_event $end
$var wire 1 $ key3_event $end
$var wire 1 % key2_event $end
$var parameter 32 & DEB $end
$var parameter 32 ' HOLD $end
$var parameter 32 ( LONG3 $end
$var reg 1 ) clk $end
$var reg 1 * key2_n $end
$var reg 1 + key3_n $end
$var reg 1 , rst_n $end
$var integer 32 - n_key2 [31:0] $end
$var integer 32 . n_key3 [31:0] $end
$var integer 32 / n_long [31:0] $end
$var integer 32 0 n_save [31:0] $end
$scope module dut $end
$var wire 1 ) clk $end
$var wire 1 * key2_n $end
$var wire 1 + key3_n $end
$var wire 1 , rst_n $end
$var wire 1 1 save_enabled $end
$var wire 1 " save_event $end
$var wire 1 ! save_locked $end
$var wire 1 2 key3_stable_n $end
$var wire 1 3 key2_stable_n $end
$var wire 1 4 guard_trigger $end
$var parameter 32 5 DEBOUNCE_CYCLES $end
$var parameter 32 6 HOLD_CYCLES $end
$var parameter 32 7 KEY3_LONG_CYCLES $end
$var parameter 2 8 ST_CHORD $end
$var parameter 2 9 ST_IDLE $end
$var parameter 2 : ST_KEY2 $end
$var parameter 2 ; ST_KEY3 $end
$var reg 1 % key2_event $end
$var reg 1 $ key3_event $end
$var reg 32 < key3_hold_count [31:0] $end
$var reg 1 # key3_long_event $end
$var reg 1 = key3_long_marked $end
$var reg 1 > save_armed $end
$var reg 2 ? state [1:0] $end
$scope module u_guard $end
$var wire 1 ) clk $end
$var wire 1 @ enabled $end
$var wire 1 * key2_n $end
$var wire 1 + key3_n $end
$var wire 1 , rst_n $end
$var parameter 32 A DB_BITS $end
$var parameter 32 B DEBOUNCE_CYCLES $end
$var parameter 32 C HOLD_BITS $end
$var parameter 32 D HOLD_CYCLES $end
$var reg 11 E hold_count [10:0] $end
$var reg 7 F key2_count [6:0] $end
$var reg 1 3 key2_stable_n $end
$var reg 1 G key2_sync1 $end
$var reg 1 H key2_sync2 $end
$var reg 7 I key3_count [6:0] $end
$var reg 1 2 key3_stable_n $end
$var reg 1 J key3_sync1 $end
$var reg 1 K key3_sync2 $end
$var reg 1 ! locked $end
$var reg 1 4 trigger $end
$upscope $end
$upscope $end
$scope task press2 $end
$upscope $end
$scope task press3 $end
$upscope $end
$upscope $end
$enddefinitions $end
$comment Show the parameter values. $end
$dumpall
b11111010000 D
b1011 C
b1100100 B
b111 A
b10 ;
b1 :
b0 9
b11 8
b1111101000 7
b11111010000 6
b1100100 5
b1111101000 (
b11111010000 '
b1100100 &
$end
#0
$dumpvars
1K
1J
b0 I
1H
1G
b0 F
b0 E
0@
b0 ?
0>
0=
b0 <
04
13
12
11
b0 0
b0 /
b0 .
b0 -
0,
1+
1*
0)
0%
0$
0#
0"
0!
$end
#5000
1)
#10000
0)
#15000
1)
#20000
0)
#25000
1)
#30000
0)
#35000
1)
#40000
0)
#45000
1)
#50000
0)
#55000
1)
#60000
0)
#65000
1)
#70000
0)
#75000
1)
#80000
0)
#85000
1)
#90000
0)
#95000
1)
#100000
0)
#105000
1)
#110000
0)
#115000
1)
#120000
0)
#125000
1)
#130000
0)
#135000
1)
#140000
0)
#145000
1)
#150000
0)
#155000
1)
#160000
0)
#165000
1)
#170000
0)
#175000
1)
#180000
0)
#185000
1)
#190000
0)
#195000
1)
#200000
0)
#205000
1)
#210000
0)
#215000
1)
#220000
0)
#225000
1)
#230000
0)
#235000
1)
#240000
0)
#245000
1)
#250000
0)
#255000
1)
#260000
0)
#265000
1)
#270000
0)
#275000
1)
#280000
0)
#285000
1)
#290000
0)
#295000
1)
#300000
0)
#305000
1)
#310000
0)
#315000
1)
#320000
0)
#325000
1)
#330000
0)
#335000
1)
#340000
0)
#345000
1)
#350000
0)
#355000
1)
#360000
0)
#365000
1)
#370000
0)
#375000
1)
#380000
0)
#385000
1)
#390000
0)
#395000
1)
#400000
0)
#405000
1)
#410000
0)
#415000
1)
#420000
0)
#425000
1)
#430000
0)
#435000
1)
#440000
0)
#445000
1)
#450000
0)
#455000
1)
#460000
0)
#465000
1)
#470000
0)
#475000
1)
#480000
0)
#485000
1)
#490000
0)
#495000
1)
#500000
0)
#505000
1)
#510000
0)
#515000
1)
#520000
0)
#525000
1)
#530000
0)
#535000
1)
#540000
0)
#545000
1)
#550000
0)
#555000
1)
#560000
0)
#565000
1)
#570000
0)
#575000
1)
#580000
0)
#585000
1)
#590000
0)
#595000
1)
#600000
0)
#605000
1)
#610000
0)
#615000
1)
#620000
0)
#625000
1)
#630000
0)
#635000
1)
#640000
0)
#645000
1)
#650000
0)
#655000
1)
#660000
0)
#665000
1)
#670000
0)
#675000
1)
#680000
0)
#685000
1)
#690000
0)
#695000
1)
#700000
0)
#705000
1)
#710000
0)
#715000
1)
#720000
0)
#725000
1)
#730000
0)
#735000
1)
#740000
0)
#745000
1)
#750000
0)
#755000
1)
#760000
0)
#765000
1)
#770000
0)
#775000
1)
#780000
0)
#785000
1)
#790000
0)
#795000
1)
#800000
0)
#805000
1)
#810000
0)
#815000
1)
#820000
0)
#825000
1)
#830000
0)
#835000
1)
#840000
0)
#845000
1)
#850000
0)
#855000
1)
#860000
0)
#865000
1)
#870000
0)
#875000
1)
#880000
0)
#885000
1)
#890000
0)
#895000
1)
#900000
0)
#905000
1)
#910000
0)
#915000
1)
#920000
0)
#925000
1)
#930000
0)
#935000
1)
#940000
0)
#945000
1)
#950000
0)
#955000
1)
#960000
0)
#965000
1)
#970000
0)
#975000
1)
#980000
0)
#985000
1)
#990000
0)
#995000
1)
#1000000
0)
1,
#1005000
1>
1)
#1010000
0)
#1015000
1)
#1020000
0)
#1025000
1)
#1030000
0)
#1035000
1)
#1040000
0)
#1045000
1)
#1050000
0)
#1055000
1)
#1060000
0)
#1065000
1)
#1070000
0)
#1075000
1)
#1080000
0)
#1085000
1)
#1090000
0)
#1095000
1)
#1100000
0)
#1105000
1)
#1110000
0)
#1115000
1)
#1120000
0)
#1125000
1)
#1130000
0)
#1135000
1)
#1140000
0)
#1145000
1)
#1150000
0)
#1155000
1)
#1160000
0)
#1165000
1)
#1170000
0)
#1175000
1)
#1180000
0)
#1185000
1)
#1190000
0)
#1195000
1)
#1200000
0)
#1205000
1)
#1210000
0)
#1215000
1)
#1220000
0)
#1225000
1)
#1230000
0)
#1235000
1)
#1240000
0)
#1245000
1)
#1250000
0)
#1255000
1)
#1260000
0)
#1265000
1)
#1270000
0)
#1275000
1)
#1280000
0)
#1285000
1)
#1290000
0)
#1295000
1)
#1300000
0)
#1305000
1)
#1310000
0)
#1315000
1)
#1320000
0)
#1325000
1)
#1330000
0)
#1335000
1)
#1340000
0)
#1345000
1)
#1350000
0)
#1355000
1)
#1360000
0)
#1365000
1)
#1370000
0)
#1375000
1)
#1380000
0)
#1385000
1)
#1390000
0)
#1395000
1)
#1400000
0)
#1405000
1)
#1410000
0)
#1415000
1)
#1420000
0)
#1425000
1)
#1430000
0)
#1435000
1)
#1440000
0)
#1445000
1)
#1450000
0)
#1455000
1)
#1460000
0)
#1465000
1)
#1470000
0)
#1475000
1)
#1480000
0)
#1485000
1)
#1490000
0)
#1495000
1)
#1500000
0)
#1505000
1)
#1510000
0)
#1515000
1)
#1520000
0)
#1525000
1)
#1530000
0)
#1535000
1)
#1540000
0)
#1545000
1)
#1550000
0)
#1555000
1)
#1560000
0)
#1565000
1)
#1570000
0)
#1575000
1)
#1580000
0)
#1585000
1)
#1590000
0)
#1595000
1)
#1600000
0)
#1605000
1)
#1610000
0)
#1615000
1)
#1620000
0)
#1625000
1)
#1630000
0)
#1635000
1)
#1640000
0)
#1645000
1)
#1650000
0)
#1655000
1)
#1660000
0)
#1665000
1)
#1670000
0)
#1675000
1)
#1680000
0)
#1685000
1)
#1690000
0)
#1695000
1)
#1700000
0)
#1705000
1)
#1710000
0)
#1715000
1)
#1720000
0)
#1725000
1)
#1730000
0)
#1735000
1)
#1740000
0)
#1745000
1)
#1750000
0)
#1755000
1)
#1760000
0)
#1765000
1)
#1770000
0)
#1775000
1)
#1780000
0)
#1785000
1)
#1790000
0)
#1795000
1)
#1800000
0)
#1805000
1)
#1810000
0)
#1815000
1)
#1820000
0)
#1825000
1)
#1830000
0)
#1835000
1)
#1840000
0)
#1845000
1)
#1850000
0)
#1855000
1)
#1860000
0)
#1865000
1)
#1870000
0)
#1875000
1)
#1880000
0)
#1885000
1)
#1890000
0)
#1895000
1)
#1900000
0)
#1905000
1)
#1910000
0)
#1915000
1)
#1920000
0)
#1925000
1)
#1930000
0)
#1935000
1)
#1940000
0)
#1945000
1)
#1950000
0)
#1955000
1)
#1960000
0)
#1965000
1)
#1970000
0)
#1975000
1)
#1980000
0)
#1985000
1)
#1990000
0)
#1995000
1)
#2000000
0)
0*
#2005000
0G
1)
#2010000
0)
#2015000
0H
1)
#2020000
0)
#2025000
b1 F
1)
#2030000
0)
#2035000
b10 F
1)
#2040000
0)
#2045000
b11 F
1)
#2050000
0)
#2055000
b100 F
1)
#2060000
0)
#2065000
b101 F
1)
#2070000
0)
#2075000
b110 F
1)
#2080000
0)
#2085000
b111 F
1)
#2090000
0)
#2095000
b1000 F
1)
#2100000
0)
#2105000
b1001 F
1)
#2110000
0)
#2115000
b1010 F
1)
#2120000
0)
#2125000
b1011 F
1)
#2130000
0)
#2135000
b1100 F
1)
#2140000
0)
#2145000
b1101 F
1)
#2150000
0)
#2155000
b1110 F
1)
#2160000
0)
#2165000
b1111 F
1)
#2170000
0)
#2175000
b10000 F
1)
#2180000
0)
#2185000
b10001 F
1)
#2190000
0)
#2195000
b10010 F
1)
#2200000
0)
#2205000
b10011 F
1)
#2210000
0)
#2215000
b10100 F
1)
#2220000
0)
#2225000
b10101 F
1)
#2230000
0)
#2235000
b10110 F
1)
#2240000
0)
#2245000
b10111 F
1)
#2250000
0)
#2255000
b11000 F
1)
#2260000
0)
#2265000
b11001 F
1)
#2270000
0)
#2275000
b11010 F
1)
#2280000
0)
#2285000
b11011 F
1)
#2290000
0)
#2295000
b11100 F
1)
#2300000
0)
#2305000
b11101 F
1)
#2310000
0)
#2315000
b11110 F
1)
#2320000
0)
#2325000
b11111 F
1)
#2330000
0)
#2335000
b100000 F
1)
#2340000
0)
#2345000
b100001 F
1)
#2350000
0)
#2355000
b100010 F
1)
#2360000
0)
#2365000
b100011 F
1)
#2370000
0)
#2375000
b100100 F
1)
#2380000
0)
#2385000
b100101 F
1)
#2390000
0)
#2395000
b100110 F
1)
#2400000
0)
#2405000
b100111 F
1)
#2410000
0)
#2415000
b101000 F
1)
#2420000
0)
#2425000
b101001 F
1)
#2430000
0)
#2435000
b101010 F
1)
#2440000
0)
#2445000
b101011 F
1)
#2450000
0)
#2455000
b101100 F
1)
#2460000
0)
#2465000
b101101 F
1)
#2470000
0)
#2475000
b101110 F
1)
#2480000
0)
#2485000
b101111 F
1)
#2490000
0)
#2495000
b110000 F
1)
#2500000
0)
#2505000
b110001 F
1)
#2510000
0)
#2515000
b110010 F
1)
#2520000
0)
#2525000
b110011 F
1)
#2530000
0)
#2535000
b110100 F
1)
#2540000
0)
#2545000
b110101 F
1)
#2550000
0)
#2555000
b110110 F
1)
#2560000
0)
#2565000
b110111 F
1)
#2570000
0)
#2575000
b111000 F
1)
#2580000
0)
#2585000
b111001 F
1)
#2590000
0)
#2595000
b111010 F
1)
#2600000
0)
#2605000
b111011 F
1)
#2610000
0)
#2615000
b111100 F
1)
#2620000
0)
#2625000
b111101 F
1)
#2630000
0)
#2635000
b111110 F
1)
#2640000
0)
#2645000
b111111 F
1)
#2650000
0)
#2655000
b1000000 F
1)
#2660000
0)
#2665000
b1000001 F
1)
#2670000
0)
#2675000
b1000010 F
1)
#2680000
0)
#2685000
b1000011 F
1)
#2690000
0)
#2695000
b1000100 F
1)
#2700000
0)
#2705000
b1000101 F
1)
#2710000
0)
#2715000
b1000110 F
1)
#2720000
0)
#2725000
b1000111 F
1)
#2730000
0)
#2735000
b1001000 F
1)
#2740000
0)
#2745000
b1001001 F
1)
#2750000
0)
#2755000
b1001010 F
1)
#2760000
0)
#2765000
b1001011 F
1)
#2770000
0)
#2775000
b1001100 F
1)
#2780000
0)
#2785000
b1001101 F
1)
#2790000
0)
#2795000
b1001110 F
1)
#2800000
0)
#2805000
b1001111 F
1)
#2810000
0)
#2815000
b1010000 F
1)
#2820000
0)
#2825000
b1010001 F
1)
#2830000
0)
#2835000
b1010010 F
1)
#2840000
0)
#2845000
b1010011 F
1)
#2850000
0)
#2855000
b1010100 F
1)
#2860000
0)
#2865000
b1010101 F
1)
#2870000
0)
#2875000
b1010110 F
1)
#2880000
0)
#2885000
b1010111 F
1)
#2890000
0)
#2895000
b1011000 F
1)
#2900000
0)
#2905000
b1011001 F
1)
#2910000
0)
#2915000
b1011010 F
1)
#2920000
0)
#2925000
b1011011 F
1)
#2930000
0)
#2935000
b1011100 F
1)
#2940000
0)
#2945000
b1011101 F
1)
#2950000
0)
#2955000
b1011110 F
1)
#2960000
0)
#2965000
b1011111 F
1)
#2970000
0)
#2975000
b1100000 F
1)
#2980000
0)
#2985000
b1100001 F
1)
#2990000
0)
#2995000
b1100010 F
1)
#3000000
0)
#3005000
b1100011 F
1)
#3010000
0)
#3015000
03
b0 F
1)
#3020000
0)
#3025000
b1 ?
1)
